{"is_source_file": false, "format": "", "description": "", "external_files": [], "external_methods": [], "published": [], "classes": [], "methods": [], "calls": [], "search-terms": [], "state": 2, "file_id": 21, "knowledge_revision": 49, "git_revision": "c39c3f920b3ca4cbfe40d4d1accf982352fb7f54", "hash": "c83afbb8edc968b5a7d97ef5a98802a7", "format-version": 4, "code-base-name": "notes_frontend", "filename": "notes_frontend/settings.gradle.kts", "revision_history": [{"49": "c39c3f920b3ca4cbfe40d4d1accf982352fb7f54"}]}